hoymiles_modbus/__init__.py
hoymiles_modbus/_modbus_tcp_client.py
hoymiles_modbus/client.py
hoymiles_modbus/datatypes.py
hoymiles_modbus-0.10.0.dist-info/LICENSE
hoymiles_modbus-0.10.0.dist-info/METADATA
hoymiles_modbus-0.10.0.dist-info/WHEEL
hoymiles_modbus-0.10.0.dist-info/RECORD
